splashgen/__init__.py
splashgen/assets/logo-default.png
splashgen/cli.py
splashgen/components/CTAButton.py
splashgen/components/SplashSite.py
splashgen/components/__init__.py
splashgen/components/form.py
splashgen/integrations.py
splashgen/templates/form.html.jinja
splashgen/templates/input.html.jinja
splashgen/templates/mailchimp_signup.html.jinja
splashgen/templates/splash_site.html.jinja
splashgen/urlexpander/__init__.py
splashgen/urlexpander/api.py
splashgen/urlexpander/constants.py
splashgenlp-0.30.0.dist-info/LICENSE
splashgenlp-0.30.0.dist-info/METADATA
splashgenlp-0.30.0.dist-info/WHEEL
splashgenlp-0.30.0.dist-info/entry_points.txt
splashgenlp-0.30.0.dist-info/RECORD
