Metadata-Version: 2.1
Name: splashgenlp
Version: 0.30.0
Summary: 
Author: benbenbang
Author-email: bn@bitbrew.dev
Requires-Python: >=3.10
Classifier: Programming Language :: Python :: 3
Classifier: Programming Language :: Python :: 3.10
Classifier: Programming Language :: Python :: 3.11
Classifier: Programming Language :: Python :: 3.12
Requires-Dist: jinja2 (>=3.1,<3.2)
Requires-Dist: numpy (>=2.1,<2.2)
Requires-Dist: pandas (>=2.2,<2.3)
Requires-Dist: pillow (>=10.4,<10.5)
Requires-Dist: py3-validate-email (>=1.0.5.post2,<2.0.0)
Requires-Dist: python-slugify (>=8.0,<8.1)
Requires-Dist: query-string (>=2020.12.3,<2021.0.0)
Requires-Dist: requests (>=2.32,<2.33)
Requires-Dist: tldextract (>=5.1,<5.2)
Requires-Dist: tqdm (>=4.66,<4.67)
Requires-Dist: unshortenit (>=0.4,<0.5)
Requires-Dist: urlextract (>=1.9,<1.10)
